setup.py
tkitWeb/__init__.py
tkitWeb/web.py
tkitWeb.egg-info/PKG-INFO
tkitWeb.egg-info/SOURCES.txt
tkitWeb.egg-info/dependency_links.txt
tkitWeb.egg-info/requires.txt
tkitWeb.egg-info/top_level.txt